ipyautoui/__init__.py
ipyautoui/_dev_maplocal_params.py
ipyautoui/_utils.py
ipyautoui/_utils_debounce.py
ipyautoui/_version.py
ipyautoui/autoanyof.py
ipyautoui/autobox.py
ipyautoui/autodisplay.py
ipyautoui/autodisplay_renderers.py
ipyautoui/autoform.py
ipyautoui/automapschema.py
ipyautoui/automapschema.yaml
ipyautoui/autoobject.py
ipyautoui/autoui.py
ipyautoui/autovjsf.py
ipyautoui/basemodel.py
ipyautoui/constants.py
ipyautoui/demo.py
ipyautoui/env.py
ipyautoui/mydocstring_display.py
ipyautoui/nullable.py
ipyautoui/vjsf.vue
ipyautoui/watch_validate.py
ipyautoui/custom/__init__.py
ipyautoui/custom/autogrid.py
ipyautoui/custom/boolean_toggle.py
ipyautoui/custom/buttonbars.py
ipyautoui/custom/combobox_mapped.py
ipyautoui/custom/datagrid.py
ipyautoui/custom/date_string.py
ipyautoui/custom/decision_branch.py
ipyautoui/custom/editgrid.py
ipyautoui/custom/editgridfile.py
ipyautoui/custom/edittsv.py
ipyautoui/custom/edittsv_with_diff_and_key_mapping.py
ipyautoui/custom/executetasks.py
ipyautoui/custom/filechooser.py
ipyautoui/custom/filedownload.py
ipyautoui/custom/filesindir.py
ipyautoui/custom/fileupload.py
ipyautoui/custom/iterable.py
ipyautoui/custom/jsonable_dict.py
ipyautoui/custom/loadproject.py
ipyautoui/custom/maplist.py
ipyautoui/custom/markdown_widget.py
ipyautoui/custom/modelrun.py
ipyautoui/custom/multi_toggle_buttons.py
ipyautoui/custom/multiselect_search.py
ipyautoui/custom/outputlogging.py
ipyautoui/custom/selectandclick.py
ipyautoui/custom/selectdir.py
ipyautoui/custom/showhide.py
ipyautoui/custom/showopenurl.py
ipyautoui/custom/svgspinner.py
ipyautoui/custom/timeelapsed.py
ipyautoui/custom/title_description.py
ipyautoui/custom/urlimagelink.py
ipyautoui/custom/widgetcaller_error.py
ipyautoui/data/12-dots-scale-rotate.svg
ipyautoui/demo_schemas/__init__.py
ipyautoui/demo_schemas/array_examples.py
ipyautoui/demo_schemas/array_object_dataframe.py
ipyautoui/demo_schemas/complex_serialization.py
ipyautoui/demo_schemas/core_ipywidgets.py
ipyautoui-0.9.0.dist-info/METADATA
ipyautoui-0.9.0.dist-info/WHEEL
ipyautoui-0.9.0.dist-info/licenses/licenses/BSD-3-Clause.txt
ipyautoui-0.9.0.dist-info/RECORD
