Metadata-Version: 2.4
Name: ipyautoui
Version: 0.9.0
Summary: wrapper that sits on top of ipywidgets and other ipy widget libraries to template / automate the creation of widget forms. Uses pydantic to create defined data-container and serialisation to JSON. Includes example patterns for adding new custom widgets.
Project-URL: Homepage, https://github.com/maxfordham/ipyautoui
Project-URL: Documentation, https://maxfordham.github.io/ipyautoui/
Project-URL: Issues, https://github.com/maxfordham/ipyautoui/issues
Project-URL: Changelog, https://github.com/maxfordham/ipyautoui/releases
Author-email: John Gunstone <gunstone.john@gmail.com>
Maintainer-email: John Gunstone <gunstone.john@gmail.com>, Olly Hensby <o.hensby@maxfordham.com>
License-Expression: BSD-3-Clause
License-File: licenses/BSD-3-Clause.txt
Keywords: form,ipyautoui,ipywidgets,jsonschema,pydantic,ui
Classifier: Development Status :: 4 - Beta
Classifier: Intended Audience :: Developers
Classifier: Natural Language :: English
Classifier: Programming Language :: Python :: 3.9
Requires-Python: <3.14,>=3.8
Requires-Dist: datamodel-code-generator<0.41,>=0.40.0
Requires-Dist: deepdiff
Requires-Dist: immutables
Requires-Dist: ipydatagrid==1.3.2
Requires-Dist: ipyfilechooser
Requires-Dist: ipython
Requires-Dist: ipyvuetify
Requires-Dist: ipywidgets>8
Requires-Dist: jsonref
Requires-Dist: markdown
Requires-Dist: numpy
Requires-Dist: openpyxl
Requires-Dist: pandas
Requires-Dist: pydantic-extra-types
Requires-Dist: pydantic-settings
Requires-Dist: pydantic>=2
Requires-Dist: pyyaml
Requires-Dist: requests
Requires-Dist: wcmatch
Requires-Dist: xlsxdatagrid<0.4,>=0.3.3
